alterego/__init__.py
alterego-0.0.0.dist-info/DESCRIPTION.rst
alterego-0.0.0.dist-info/METADATA
alterego-0.0.0.dist-info/RECORD
alterego-0.0.0.dist-info/WHEEL
alterego-0.0.0.dist-info/metadata.json
alterego-0.0.0.dist-info/top_level.txt
sapiens/__init__.py
