Metadata-Version: 2.0
Name: alterego
Version: 0.0.0
Summary: alterego library.
Home-page: UNKNOWN
Author: Jim Fan
Author-email: UNKNOWN
License: GPLv3
Platform: UNKNOWN
Classifier: Development Status :: 1 - Planning
Classifier: Programming Language :: Python :: 3
